Workbook

Sheet Software Inventory
A1: Ubuntu Innovations (Pty) Ltd — Software Inventory
A2: Prepared by: Luthando | Week 1 Deliverable | Google IT Support Professional Certificate Capstone | Version 2: vendor and product names added
A3: Yellow = new row added in this version. Full detail per product (vendor, edition, seats, licence type) is on the 'Product Register' sheet.
A5: Department | B5: Standard Software | C5: Department-Specific Software | D5: Purpose | E5: Licensing Notes
A6: All Departments (baseline) | B6: Windows 11 Pro (Microsoft) on 17 devices; Ubuntu Desktop 26.04 LTS (Canonical) on the 8 developer PCs; Microsoft 365 Business Premium (Outlook, Word, Excel, PowerPoint, Teams, OneDrive/SharePoint); Microsoft Defender for Business (Windows endpoint security); ClamAV + UFW firewall (Ubuntu); Bitwarden Teams (password manager); Microsoft Edge / Google Chrome (Firefox on Ubuntu) | C6: — | D6: Daily operations, communication and device protection | E6: Microsoft 365 Business Premium: 25 per-user subscriptions (includes Defender for Business and Intune device management). Windows 11 Pro is OEM with the hardware. Ubuntu and ClamAV are free/open source. Bitwarden Teams: 25 seats.
A7: Executive Management | B7: Microsoft 365 Business Premium (Outlook, Word, Excel, PowerPoint, Teams), web browser, Meraki Client VPN (laptops) | C7: HubSpot CRM (viewer seats for sales dashboards); Adobe Acrobat Pro (contracts and signing) | D7: Management, communication, reporting and decision-making | E7: 3 seats. Acrobat Pro is a per-user subscription and is optional; Meraki Client VPN is included with the firewall.
A8: Finance | B8: Microsoft 365 Business Premium (Outlook, Excel, Teams), web browser | C8: Sage Accounting (or Xero) for the ledger, invoicing and VAT; SimplePay (or Sage Payroll) for payroll; Adobe Acrobat Pro | D8: Financial records, calculations, reporting and administration | E8: 4 seats. Accounting is a per-user annual/monthly subscription; payroll is billed per employee (25) with 2 Finance administrators. Check SARS/VAT compatibility.
A9: Human Resources | B9: Microsoft 365 Business Premium (Word, Excel, Outlook, Teams), web browser | C9: BambooHR (or Sage HR) for records, leave and onboarding; SharePoint HR document library (in Microsoft 365) as the document management system; SimplePay access for 2 payroll administrators; Adobe Acrobat Pro | D9: Employee records, documentation and communication | E9: 3 seats. HR system is billed per employee (25). Holds personal information, so POPIA controls apply (restricted access, encryption, retention).
A10: Sales and Marketing | B10: Microsoft 365 Business Premium (Outlook, Word, Excel, PowerPoint, Teams), web browser, Meraki Client VPN (2 field laptops) | C10: HubSpot CRM Starter (7 seats); Canva Teams (3 seats); Mailchimp (3 seats); Adobe Creative Cloud (2 seats, optional) | D10: Customer communication, marketing activities and reporting | E10: 7 seats for the CRM. Marketing tools depend on tier and contact-list size and must respect POPIA opt-in rules.
A11: Software Development | B11: Ubuntu Desktop 26.04 LTS, Microsoft 365 (email and Teams), Firefox / Chrome | C11: Visual Studio Code (Microsoft); Git; GitHub Team (GitHub); Docker Engine; VirtualBox (Oracle) or KVM/QEMU; Jira (Atlassian, free plan) or Trello; JetBrains IDE (4 seats, optional) | D11: Software development, testing and project work | E11: 8 seats. Most tools are free/open source. GitHub Team and JetBrains are per-user subscriptions; the Jira free plan has a user cap (verify current limit).
A12: Infrastructure (company-wide) | B12: Synology DiskStation Manager with Hyper Backup / Active Backup for Business (NAS); Cisco Business Dashboard / Cisco Business app (switch and Wi-Fi) | C12: Cisco Meraki MX68 Advanced Security licence and Dashboard; Backblaze B2 (or Wasabi / Azure Blob) offsite backup; Freshdesk free plan or osTicket (helpdesk tickets) | D12: File sharing, backup, network security and IT support | E12: Meraki licence is per device (1, 3 or 5-year) and the firewall needs an active licence to keep working. NAS and Cisco Business tools have no extra licence. Cloud backup is billed per TB.
A14: Note: Software mapped from the approved Business Requirements Analysis (5 departments, 25 employees). Vendor and product names are recommendations: confirm editions, prices and free-tier limits with each vendor before final submission.

Sheet Product Register
A1: Product Register (vendor, product, edition and seats)
A2: Department columns = users (or devices) that need the software. Blue = inputs; Total Users is a formula.
E4: Headcount | F4: 3 | G4: 4 | H4: 3 | I4: 7 | J4: 8 | L4: =SUM(F4:J4) -> 25
A5: Ref | B5: Vendor | C5: Product | D5: Edition / Version | E5: Category | F5: Exec | G5: Finance | H5: HR | I5: Sales & Mktg | J5: Dev | K5: Infra | L5: Total Users | M5: Licence Type | N5: Licensing Model and Notes | O5: Priority
A6: SW-01 | B6: Microsoft | C6: Windows 11 Pro | D6: Current release | E6: Operating system | F6: 3 | G6: 4 | H6: 3 | I6: 7 | J6: 0 | K6: 0 | L6: =SUM(F6:K6) -> 17 | M6: Included / OEM | N6: OEM licence supplied with the hardware. Managed by Intune; BitLocker enabled. | O6: Essential
A7: SW-02 | B7: Canonical | C7: Ubuntu Desktop | D7: 26.04 LTS (24.04 LTS also supported) | E7: Operating system | F7: 0 | G7: 0 | H7: 0 | I7: 0 | J7: 8 | K7: 0 | L7: =SUM(F7:K7) -> 8 | M7: Open source / free | N7: Open source. 26.04 LTS was released in April 2026 with security updates to April 2031. Enable full-disk encryption and unattended security updates. | O7: Essential
A8: SW-03 | B8: Microsoft | C8: Microsoft 365 Business Premium | D8: Per user | E8: Productivity / identity / device mgmt | F8: 3 | G8: 4 | H8: 3 | I8: 7 | J8: 8 | K8: 0 | L8: =SUM(F8:K8) -> 25 | M8: Subscription | N8: Per-user subscription (25). Email, Office apps, Teams, OneDrive/SharePoint, Entra ID with MFA, Intune and Defender for Business in one bundle. | O8: Essential
A9: SW-04 | B9: Microsoft | C9: Defender for Business | D9: Included in SW-03 | E9: Endpoint security (AV/EDR) | F9: 3 | G9: 4 | H9: 3 | I9: 7 | J9: 0 | K9: 0 | L9: =SUM(F9:K9) -> 17 | M9: Included / OEM | N9: Covers the 17 Windows devices at no extra cost. | O9: Essential
A10: SW-05 | B10: Cisco (ClamAV) / Canonical | C10: ClamAV + UFW | D10: Current packages | E10: Endpoint security (Linux) | F10: 0 | G10: 0 | H10: 0 | I10: 0 | J10: 8 | K10: 0 | L10: =SUM(F10:K10) -> 8 | M10: Open source / free | N10: Open source antivirus and host firewall for the Ubuntu PCs. EDR for Linux to be confirmed with the security vendor. | O10: Essential
A11: SW-06 | B11: Bitwarden | C11: Bitwarden Teams | D11: Teams Organization | E11: Security | F11: 3 | G11: 4 | H11: 3 | I11: 7 | J11: 8 | K11: 0 | L11: =SUM(F11:K11) -> 25 | M11: Subscription | N11: Per-user subscription (25 seats). Shared collections per department. | O11: Essential
A12: SW-07 | B12: Microsoft / Google / Mozilla | C12: Edge or Chrome (Firefox on Ubuntu) | D12: Current | E12: Productivity | F12: 3 | G12: 4 | H12: 3 | I12: 7 | J12: 8 | K12: 0 | L12: =SUM(F12:K12) -> 25 | M12: Open source / free | N12: Free. Extensions restricted by policy. | O12: Essential
A13: SW-08 | B13: Cisco (Meraki) | C13: Meraki Client VPN | D13: Built into MX68 | E13: Networking / security | F13: 3 | G13: 0 | H13: 0 | I13: 2 | J13: 0 | K13: 0 | L13: =SUM(F13:K13) -> 5 | M13: Included / OEM | N13: IPsec client VPN uses the operating system's built-in VPN client. For Executive and the 2 field-sales laptops. | O13: Essential
A14: SW-09 | B14: Sage / Xero | C14: Sage Accounting or Xero | D14: Per plan | E14: Business application | F14: 0 | G14: 4 | H14: 0 | I14: 0 | J14: 0 | K14: 0 | L14: =SUM(F14:K14) -> 4 | M14: Subscription | N14: Per-company plan with per-user seats. Confirm VAT/SARS features. | O14: Essential
A15: SW-10 | B15: SimplePay / Sage | C15: SimplePay or Sage Payroll | D15: Per employee | E15: Business application | F15: 0 | G15: 2 | H15: 2 | I15: 0 | J15: 0 | K15: 0 | L15: =SUM(F15:K15) -> 4 | M15: Subscription | N15: Billed per employee (25). Access limited to 2 Finance and 2 HR administrators. | O15: Essential
A16: SW-11 | B16: Adobe | C16: Acrobat Pro | D16: Per user | E16: Productivity | F16: 3 | G16: 4 | H16: 3 | I16: 0 | J16: 0 | K16: 0 | L16: =SUM(F16:K16) -> 10 | M16: Subscription | N16: Per-user subscription. Optional: Microsoft 365 handles basic PDF needs. | O16: Optional
A17: SW-12 | B17: BambooHR / Sage | C17: BambooHR or Sage HR | D17: Per employee | E17: Business application | F17: 0 | G17: 0 | H17: 3 | I17: 0 | J17: 0 | K17: 0 | L17: =SUM(F17:K17) -> 3 | M17: Subscription | N17: Billed per employee (25). Personal information: POPIA controls apply. | O17: Essential
... A34: SW-29 | B34: KnowBe4 (or in-house) | C34: Security awareness training | D34: Per user | E34: Security | F34: 0 | G34: 0 | H34: 0 | I34: 0 | J34: 0 | K34: 1 | L34: =SUM(F34:K34) -> 1 | M34: Subscription | N34: Optional: in-house sessions are covered in the Week 3 Security Awareness Outline. | O34: Optional

Sheet Licensing Summary
A1: Licensing Summary
A2: All figures are formulas reading the Product Register.
A4: By licence type | B4: Number of products
A5: Subscription | B5: =COUNTIF('Product Register'!$M$6:$M$34,A5) -> 15
A6: Open source / free | B6: =COUNTIF('Product Register'!$M$6:$M$34,A6) -> 10
A7: Included / OEM | B7: =COUNTIF('Product Register'!$M$6:$M$34,A7) -> 4
A8: Total products | B8: =SUM(B5:B7) -> 29
A10: By priority | B10: Number of products
A11: Essential | B11: =COUNTIF('Product Register'!$O$6:$O$34,A11) -> 19
A12: Recommended | B12: =COUNTIF('Product Register'!$O$6:$O$34,A12) -> 6
A13: Optional | B13: =COUNTIF('Product Register'!$O$6:$O$34,A13) -> 4
A14: Total products | B14: =SUM(B11:B13) -> 29
A15: Check: both totals match | B15: =IF(B8=B14,"OK","CHECK") -> OK
A17: Department | B17: Products used | C17: Headcount
A18: Executive Management | B18: =COUNTIF('Product Register'!$F$6:$F$34,">0") -> 8 | C18: ='Product Register'!F4 -> 3
A19: Finance | B19: =COUNTIF('Product Register'!$G$6:$G$34,">0") -> 8 | C19: ='Product Register'!G4 -> 4
A20: Human Resources | B20: =COUNTIF('Product Register'!$H$6:$H$34,">0") -> 8 | C20: ='Product Register'!H4 -> 3
A21: Sales and Marketing | B21: =COUNTIF('Product Register'!$I$6:$I$34,">0") -> 10 | C21: ='Product Register'!I4 -> 7
A22: Software Development | B22: =COUNTIF('Product Register'!$J$6:$J$34,">0") -> 12 | C22: ='Product Register'!J4 -> 8

Sheet Change Log
A1: Change Log: what changed from your first version
A3: Item | B3: First version | C3: This version | D3: Reason
A4: Product names | B4: Generic categories (e.g. 'productivity suite', 'antivirus') | C4: Vendor, product and edition for every item | D4: Requested by the networking team members; also needed for licensing.
A5: Operating systems | B5: Not stated | C5: Windows 11 Pro (17 devices), Ubuntu Desktop 26.04 LTS (8 developer PCs) | D5: Ubuntu 26.04 LTS is the current LTS (released April 2026); developers on Ubuntu link to the Week 2 Linux tasks.
A6: Endpoint security | B6: Per-seat antivirus (25 licences) | C6: Microsoft Defender for Business (included in Microsoft 365 Business Premium) + ClamAV/UFW on Ubuntu | D6: Avoids buying a separate antivirus for 25 devices.
A7: Infrastructure row | B7: Not included | C7: New row: NAS software, Meraki licence, cloud backup, helpdesk | D7: The Cisco Meraki firewall needs an active licence, and backup needs software and cloud storage.
A8: Document management (HR) | B8: Document management system | C8: SharePoint HR document library (in Microsoft 365) + NAS /Company/HR folder | D8: No separate product is needed.
A9: Product Register + summary sheets | B9: None | C9: Seat counts by department with formula totals and a licensing summary | D9: Gives a clear licensing plan for the final report.
